{"name":"Breakout.link","tagline":"breakout board link resource","body":"\r\n##*stackable breakout board link - 8 channels* *link the breakout board as your want.*\r\n\r\n[Order the boards form aliexpress](http://www.aliexpress.com/store/1995360)\r\n\r\n![description](/images/description.png)\r\n\r\n\r\n*TI lauchpad breakout link board*\r\n\r\n*match for board MSP LaunchPad, C2000 Launchpad, Tiva C Launchapd, Hercules Launchpad, C3200 Launchpad*\r\n> ![description](/images/lp-40.png)\r\n> ![lauchpad breakout link](/images/lp-40.jpg)\r\n\r\n*Freescale breakout*\r\n\r\n*match for KE02Z KE04Z KE06ZKL02Z KL05Z KL25Z KL26Z KL27Z KL46Z*\r\n*match for arduino UNO board*\r\n>![Freescale frong](/images/fdmFront.png)\r\n>![Freescale back](/images/fdmBack.png)\r\n>![Freescale stack](/images/fdmStack.png)\r\n\r\n*Launchpad breakout*\r\n\r\n*match for board MSP LaunchPad, C2000 Launchpad, Tiva C Launchapd, Hercules Launchpad, C3200 Launchpad*\r\n>![Launchpad frong](/images/lpFront.png)\r\n>![Launchpad back](/images/lpBack.png)\r\n>![Launchpad stack](/images/lpStack.png)\r\n\r\n*NxP dip40 breakout*\r\n\r\n*match for board nxp 40pin 900mil board*\r\n>![NxP dip40 frong](/images/xpFront.png)\r\n>![NxP dip40 back](/images/xpBack.png)\r\n>![NxP dip40 stack](/images/xpStack.png)\r\n\r\n*st discovery 64 breakout*\r\n>![st discovery 64 frong](/images/dis64Front.png)\r\n>![st discovery 64 back](/images/dis64Back.png)\r\n>![st discovery 64 stack](/images/dis64Stack.png)\r\n\r\n*st discovery 100 breakout*\r\n>![st discovery 100 frong](/images/dis100Front.png)\r\n>![st discovery 100 back](/images/dis100Back.png)\r\n>![st discovery 100 stack](/images/dis100Stack.png)\r\n\r\n*st discovery 144 breakout*\r\n>![st discovery 144 frong](/images/dis144Front.png)\r\n>![st discovery 144 back](/images/dis144Back.png)\r\n>![st discovery 144 stack](/images/dis144Stack.png)\r\n\r\n*st nucleo 32 breakout*\r\n>![st nucleo 32 frong](/images/nu32Front.png)\r\n>![st nucleo 32 back](/images/nu32Back.png)\r\n>![st nucleo 32 stack](/images/nu32Stack.png)\r\n\r\n*st nucleo 64 breakout*\r\n>![st nucleo 64 frong](/images/nu64Front.png)\r\n>![st nucleo 64 back](/images/nu64Back.png)\r\n>![st nucleo 64 stack](/images/nu64Stack.png)\r\n\r\n*contact us info@breakout.link*\r\n","google":"","note":"Don't delete this file! It's used internally to help with page regeneration."}